{
  "_fv": 79,
  "_type": "structure",
  "definition": {
    "structure": "bean_camp",
    "projection": "terrain_matching",
    "ignoredBlocks": [
      {
        "value": "Blocks.STRUCTURE_BLOCK"
      },
      {
        "value": "Blocks.WATER"
      }
    ],
    "spacing": 14,
    "separation": 12,
    "restrictionBiomes": [
      {
        "value": "CUSTOM:Grassland"
      }
    ],
    "terrainAdaptation": "none",
    "generationStep": "SURFACE_STRUCTURES",
    "surfaceDetectionType": "WORLD_SURFACE_WG",
    "useStartHeight": false,
    "startHeightProviderType": "UNIFORM",
    "startHeightMin": 120,
    "startHeightMax": 150,
    "size": 1,
    "maxDistanceFromCenter": 64,
    "jigsawPools": []
  }
}